function_save/__init__.py
function_save/function_save_pkg.py
function_save-0.1.1.dist-info/METADATA
function_save-0.1.1.dist-info/WHEEL
function_save-0.1.1.dist-info/top_level.txt
function_save-0.1.1.dist-info/RECORD
